bioresource/__init__.py
bioresource/cli.py
bioresource/config.py
bioresource/lib.py
bioresource/pipelines.py
bioresource/versions.py
BioResource-0.1.5.dist-info/LICENSE
BioResource-0.1.5.dist-info/METADATA
BioResource-0.1.5.dist-info/WHEEL
BioResource-0.1.5.dist-info/top_level.txt
BioResource-0.1.5.dist-info/RECORD
