Metadata-Version: 2.1
Name: BioResource
Version: 0.1.5
Summary: A tool for easy and fast access to biological big data
Home-page: https://github.com/SouthernCD/BioResource
Author: Yuxing Xu
Author-email: xuyuxing@mail.kib.ac.cn
License: UNKNOWN
Platform: UNKNOWN
Requires-Python: >=3.5
License-File: LICENSE
Requires-Dist: toolbiox (>=0.0.13beautifulsoup4>=4.11.1)
Requires-Dist: requests (>=2.28.1)
Requires-Dist: retry
